{"decls":[{"kind":"export","names":["scan.events.check_finished_v1","scan.events.check_started_v1","scan.events.dimension_finished_v1","scan.events.dimension_started_v1","scan.events.finding_emitted_v1","scan.events.metrics_dimension_v1","scan.events.metrics_usage_v1","scan.events.scan_finished_v1","scan.events.scan_started_v1","scan.events.score_preview_v1","scan.events.stage_finished_v1","scan.events.stage_started_v1"]},{"body":["begin",["let","doc0",["ext.data_model.doc_ok","event_value"]],["std.cli.jsonl.encode_v1",["bytes.view","doc0"]]],"kind":"defn","name":"scan.events._event_line_v1","params":[{"name":"event_value","ty":"bytes_view"}],"result":"bytes"},{"body":["begin",["let","line",["scan.events._event_line_v1",["bytes.view","event_value"]]],["std.vec.extend_bytes","events_out",["bytes.view","line"]]],"kind":"defn","name":"scan.events._push_value_v1","params":[{"name":"events_out","ty":"vec_u8"},{"name":"event_value","ty":"bytes"}],"result":"vec_u8"},{"body":["begin",["let","b",["std.vec.as_bytes","events_out"]],["let","v",["bytes.view","b"]],["let","n",["view.len","v"]],["let","seq",0],["for","i",0,"n",["begin",["if",["=",["view.get_u8","v","i"],10],["set","seq",["+","seq",1]],0],0]],"seq"],"kind":"defn","name":"scan.events._seq_next_v1","params":[{"name":"events_out","ty":"vec_u8"}],"result":"i32"},{"body":["scan.time.now_rfc3339_utc_v1"],"kind":"defn","name":"scan.events._ts_v1","params":[],"result":"bytes"},{"body":["begin",["let","ts",["scan.events._ts_v1"]],["let","status","status_in"],["if",["!=","err_code",0],["set","status",["bytes.view_lit","fail"]],0],["if",["=",["bytes.len","status"],0],["set","status",["bytes.view_lit","unknown"]],0],["let","pl",["std.vec.with_capacity",512]],["let","k",0],["set","pl",["scan.dm.payload_push_entry_v1","pl",["bytes.view_lit","dimension"],["scan.model.dm_string_v1","dimension"]]],["set","k",["+","k",1]],["set","pl",["scan.dm.payload_push_entry_v1","pl",["bytes.view_lit","check_id"],["scan.model.dm_string_v1","check_id"]]],["set","k",["+","k",1]],["set","pl",["scan.dm.payload_push_entry_v1","pl",["bytes.view_lit","label"],["scan.model.dm_string_v1","label"]]],["set","k",["+","k",1]],["set","pl",["scan.dm.payload_push_entry_v1","pl",["bytes.view_lit","status"],["scan.model.dm_string_v1","status"]]],["set","k",["+","k",1]],["set","pl",["scan.dm.payload_push_entry_v1","pl",["bytes.view_lit","err_code"],["scan.model.dm_number_i32_v1","err_code"]]],["set","k",["+","k",1]],["set","pl",["scan.dm.payload_push_entry_v1","pl",["bytes.view_lit","elapsed_ms"],["scan.model.dm_number_i32_v1","elapsed_ms"]]],["set","k",["+","k",1]],["set","pl",["scan.dm.payload_push_entry_v1","pl",["bytes.view_lit","phase"],["scan.model.dm_string_v1",["bytes.view_lit","checks"]]]],["set","k",["+","k",1]],["set","pl",["scan.dm.payload_push_entry_v1","pl",["bytes.view_lit","run_id"],["scan.model.dm_string_v1","run_id"]]],["set","k",["+","k",1]],["set","pl",["scan.dm.payload_push_entry_v1","pl",["bytes.view_lit","seq"],["scan.model.dm_number_i32_v1","seq"]]],["set","k",["+","k",1]],["set","pl",["scan.dm.payload_push_entry_v1","pl",["bytes.view_lit","timestamp"],["scan.model.dm_string_v1",["bytes.view","ts"]]]],["set","k",["+","k",1]],["set","pl",["scan.dm.payload_push_entry_v1","pl",["bytes.view_lit","type"],["scan.model.dm_string_v1",["bytes.view_lit","scan.check.finished"]]]],["set","k",["+","k",1]],["set","pl",["scan.dm.payload_push_entry_v1","pl",["bytes.view_lit","payload"],["scan.dm.empty_map_v1"]]],["set","k",["+","k",1]],["let","pl_b",["std.vec.as_bytes","pl"]],["let","event_value",["scan.dm.map_from_entries_v1","k",["bytes.view","pl_b"]]],["scan.events._event_line_v1",["bytes.view","event_value"]]],"kind":"defn","name":"scan.events.check_finished_v1","params":[{"name":"seq","ty":"i32"},{"name":"run_id","ty":"bytes_view"},{"name":"dimension","ty":"bytes_view"},{"name":"check_id","ty":"bytes_view"},{"name":"label","ty":"bytes_view"},{"name":"status_in","ty":"bytes_view"},{"name":"elapsed_ms","ty":"i32"},{"name":"err_code","ty":"i32"}],"result":"bytes"},{"body":["begin",["let","ts",["scan.events._ts_v1"]],["let","pl",["std.vec.with_capacity",512]],["let","k",0],["set","pl",["scan.dm.payload_push_entry_v1","pl",["bytes.view_lit","dimension"],["scan.model.dm_string_v1","dimension"]]],["set","k",["+","k",1]],["set","pl",["scan.dm.payload_push_entry_v1","pl",["bytes.view_lit","check_id"],["scan.model.dm_string_v1","check_id"]]],["set","k",["+","k",1]],["set","pl",["scan.dm.payload_push_entry_v1","pl",["bytes.view_lit","label"],["scan.model.dm_string_v1","label"]]],["set","k",["+","k",1]],["set","pl",["scan.dm.payload_push_entry_v1","pl",["bytes.view_lit","phase"],["scan.model.dm_string_v1",["bytes.view_lit","checks"]]]],["set","k",["+","k",1]],["set","pl",["scan.dm.payload_push_entry_v1","pl",["bytes.view_lit","run_id"],["scan.model.dm_string_v1","run_id"]]],["set","k",["+","k",1]],["set","pl",["scan.dm.payload_push_entry_v1","pl",["bytes.view_lit","seq"],["scan.model.dm_number_i32_v1","seq"]]],["set","k",["+","k",1]],["set","pl",["scan.dm.payload_push_entry_v1","pl",["bytes.view_lit","timestamp"],["scan.model.dm_string_v1",["bytes.view","ts"]]]],["set","k",["+","k",1]],["set","pl",["scan.dm.payload_push_entry_v1","pl",["bytes.view_lit","type"],["scan.model.dm_string_v1",["bytes.view_lit","scan.check.started"]]]],["set","k",["+","k",1]],["set","pl",["scan.dm.payload_push_entry_v1","pl",["bytes.view_lit","payload"],["scan.dm.empty_map_v1"]]],["set","k",["+","k",1]],["let","pl_b",["std.vec.as_bytes","pl"]],["let","event_value",["scan.dm.map_from_entries_v1","k",["bytes.view","pl_b"]]],["scan.events._event_line_v1",["bytes.view","event_value"]]],"kind":"defn","name":"scan.events.check_started_v1","params":[{"name":"seq","ty":"i32"},{"name":"run_id","ty":"bytes_view"},{"name":"dimension","ty":"bytes_view"},{"name":"check_id","ty":"bytes_view"},{"name":"label","ty":"bytes_view"}],"result":"bytes"},{"body":["begin",["let","ts",["scan.events._ts_v1"]],["let","status","status_in"],["if",["!=","err_code",0],["set","status",["bytes.view_lit","fail"]],0],["if",["=",["bytes.len","status"],0],["set","status",["bytes.view_lit","unknown"]],0],["let","pl",["std.vec.with_capacity",512]],["let","k",0],["set","pl",["scan.dm.payload_push_entry_v1","pl",["bytes.view_lit","dimension"],["scan.model.dm_string_v1","dimension"]]],["set","k",["+","k",1]],["set","pl",["scan.dm.payload_push_entry_v1","pl",["bytes.view_lit","status"],["scan.model.dm_string_v1","status"]]],["set","k",["+","k",1]],["set","pl",["scan.dm.payload_push_entry_v1","pl",["bytes.view_lit","err_code"],["scan.model.dm_number_i32_v1","err_code"]]],["set","k",["+","k",1]],["set","pl",["scan.dm.payload_push_entry_v1","pl",["bytes.view_lit","phase"],["scan.model.dm_string_v1",["bytes.view_lit","dimensions"]]]],["set","k",["+","k",1]],["set","pl",["scan.dm.payload_push_entry_v1","pl",["bytes.view_lit","run_id"],["scan.model.dm_string_v1","run_id"]]],["set","k",["+","k",1]],["set","pl",["scan.dm.payload_push_entry_v1","pl",["bytes.view_lit","seq"],["scan.model.dm_number_i32_v1","seq"]]],["set","k",["+","k",1]],["set","pl",["scan.dm.payload_push_entry_v1","pl",["bytes.view_lit","timestamp"],["scan.model.dm_string_v1",["bytes.view","ts"]]]],["set","k",["+","k",1]],["set","pl",["scan.dm.payload_push_entry_v1","pl",["bytes.view_lit","type"],["scan.model.dm_string_v1",["bytes.view_lit","scan.dimension.finished"]]]],["set","k",["+","k",1]],["set","pl",["scan.dm.payload_push_entry_v1","pl",["bytes.view_lit","payload"],["scan.dm.empty_map_v1"]]],["set","k",["+","k",1]],["let","pl_b",["std.vec.as_bytes","pl"]],["let","event_value",["scan.dm.map_from_entries_v1","k",["bytes.view","pl_b"]]],["scan.events._event_line_v1",["bytes.view","event_value"]]],"kind":"defn","name":"scan.events.dimension_finished_v1","params":[{"name":"seq","ty":"i32"},{"name":"run_id","ty":"bytes_view"},{"name":"dimension","ty":"bytes_view"},{"name":"status_in","ty":"bytes_view"},{"name":"err_code","ty":"i32"}],"result":"bytes"},{"body":["begin",["let","ts",["scan.events._ts_v1"]],["let","pl",["std.vec.with_capacity",512]],["let","k",0],["set","pl",["scan.dm.payload_push_entry_v1","pl",["bytes.view_lit","dimension"],["scan.model.dm_string_v1","dimension"]]],["set","k",["+","k",1]],["set","pl",["scan.dm.payload_push_entry_v1","pl",["bytes.view_lit","phase"],["scan.model.dm_string_v1",["bytes.view_lit","dimensions"]]]],["set","k",["+","k",1]],["set","pl",["scan.dm.payload_push_entry_v1","pl",["bytes.view_lit","run_id"],["scan.model.dm_string_v1","run_id"]]],["set","k",["+","k",1]],["set","pl",["scan.dm.payload_push_entry_v1","pl",["bytes.view_lit","seq"],["scan.model.dm_number_i32_v1","seq"]]],["set","k",["+","k",1]],["set","pl",["scan.dm.payload_push_entry_v1","pl",["bytes.view_lit","timestamp"],["scan.model.dm_string_v1",["bytes.view","ts"]]]],["set","k",["+","k",1]],["set","pl",["scan.dm.payload_push_entry_v1","pl",["bytes.view_lit","type"],["scan.model.dm_string_v1",["bytes.view_lit","scan.dimension.started"]]]],["set","k",["+","k",1]],["set","pl",["scan.dm.payload_push_entry_v1","pl",["bytes.view_lit","payload"],["scan.dm.empty_map_v1"]]],["set","k",["+","k",1]],["let","pl_b",["std.vec.as_bytes","pl"]],["let","event_value",["scan.dm.map_from_entries_v1","k",["bytes.view","pl_b"]]],["scan.events._event_line_v1",["bytes.view","event_value"]]],"kind":"defn","name":"scan.events.dimension_started_v1","params":[{"name":"seq","ty":"i32"},{"name":"run_id","ty":"bytes_view"},{"name":"dimension","ty":"bytes_view"}],"result":"bytes"},{"body":["begin",["let","ts",["scan.events._ts_v1"]],["let","pl",["std.vec.with_capacity",768]],["let","k",0],["set","pl",["scan.dm.payload_push_entry_v1","pl",["bytes.view_lit","type"],["scan.model.dm_string_v1",["bytes.view_lit","scan.finding.emitted"]]]],["set","k",["+","k",1]],["set","pl",["scan.dm.payload_push_entry_v1","pl",["bytes.view_lit","run_id"],["scan.model.dm_string_v1","run_id"]]],["set","k",["+","k",1]],["set","pl",["scan.dm.payload_push_entry_v1","pl",["bytes.view_lit","seq"],["scan.model.dm_number_i32_v1","seq"]]],["set","k",["+","k",1]],["set","pl",["scan.dm.payload_push_entry_v1","pl",["bytes.view_lit","timestamp"],["scan.model.dm_string_v1",["bytes.view","ts"]]]],["set","k",["+","k",1]],["set","pl",["scan.dm.payload_push_entry_v1","pl",["bytes.view_lit","phase"],["scan.model.dm_string_v1",["bytes.view_lit","findings"]]]],["set","k",["+","k",1]],["set","pl",["scan.dm.payload_push_entry_v1","pl",["bytes.view_lit","dimension"],["scan.model.dm_string_v1","dimension"]]],["set","k",["+","k",1]],["set","pl",["scan.dm.payload_push_entry_v1","pl",["bytes.view_lit","code"],["scan.model.dm_string_v1","code"]]],["set","k",["+","k",1]],["set","pl",["scan.dm.payload_push_entry_v1","pl",["bytes.view_lit","severity"],["scan.model.dm_string_v1","severity"]]],["set","k",["+","k",1]],["set","pl",["scan.dm.payload_push_entry_v1","pl",["bytes.view_lit","payload"],["scan.dm.empty_map_v1"]]],["set","k",["+","k",1]],["let","pl_b",["std.vec.as_bytes","pl"]],["let","event_value",["scan.dm.map_from_entries_v1","k",["bytes.view","pl_b"]]],["scan.events._event_line_v1",["bytes.view","event_value"]]],"kind":"defn","name":"scan.events.finding_emitted_v1","params":[{"name":"seq","ty":"i32"},{"name":"run_id","ty":"bytes_view"},{"name":"dimension","ty":"bytes_view"},{"name":"code","ty":"bytes_view"},{"name":"severity","ty":"bytes_view"}],"result":"bytes"},{"body":["begin",["let","ts",["scan.events._ts_v1"]],["let","pl",["std.vec.with_capacity",768]],["let","k",0],["set","pl",["scan.dm.payload_push_entry_v1","pl",["bytes.view_lit","type"],["scan.model.dm_string_v1",["bytes.view_lit","scan.metrics.dimension"]]]],["set","k",["+","k",1]],["set","pl",["scan.dm.payload_push_entry_v1","pl",["bytes.view_lit","run_id"],["scan.model.dm_string_v1","run_id"]]],["set","k",["+","k",1]],["set","pl",["scan.dm.payload_push_entry_v1","pl",["bytes.view_lit","seq"],["scan.model.dm_number_i32_v1","seq"]]],["set","k",["+","k",1]],["set","pl",["scan.dm.payload_push_entry_v1","pl",["bytes.view_lit","timestamp"],["scan.model.dm_string_v1",["bytes.view","ts"]]]],["set","k",["+","k",1]],["set","pl",["scan.dm.payload_push_entry_v1","pl",["bytes.view_lit","phase"],["scan.model.dm_string_v1",["bytes.view_lit","metrics"]]]],["set","k",["+","k",1]],["set","pl",["scan.dm.payload_push_entry_v1","pl",["bytes.view_lit","dimension"],["scan.model.dm_string_v1","dimension"]]],["set","k",["+","k",1]],["set","pl",["scan.dm.payload_push_entry_v1","pl",["bytes.view_lit","payload"],["scan.dm.empty_map_v1"]]],["set","k",["+","k",1]],["let","pl_b",["std.vec.as_bytes","pl"]],["let","event_value",["scan.dm.map_from_entries_v1","k",["bytes.view","pl_b"]]],["scan.events._event_line_v1",["bytes.view","event_value"]]],"kind":"defn","name":"scan.events.metrics_dimension_v1","params":[{"name":"seq","ty":"i32"},{"name":"run_id","ty":"bytes_view"},{"name":"dimension","ty":"bytes_view"}],"result":"bytes"},{"body":["begin",["let","ts",["scan.events._ts_v1"]],["let","pl",["std.vec.with_capacity",768]],["let","k",0],["set","pl",["scan.dm.payload_push_entry_v1","pl",["bytes.view_lit","type"],["scan.model.dm_string_v1",["bytes.view_lit","scan.metrics.usage"]]]],["set","k",["+","k",1]],["set","pl",["scan.dm.payload_push_entry_v1","pl",["bytes.view_lit","run_id"],["scan.model.dm_string_v1","run_id"]]],["set","k",["+","k",1]],["set","pl",["scan.dm.payload_push_entry_v1","pl",["bytes.view_lit","seq"],["scan.model.dm_number_i32_v1","seq"]]],["set","k",["+","k",1]],["set","pl",["scan.dm.payload_push_entry_v1","pl",["bytes.view_lit","timestamp"],["scan.model.dm_string_v1",["bytes.view","ts"]]]],["set","k",["+","k",1]],["set","pl",["scan.dm.payload_push_entry_v1","pl",["bytes.view_lit","phase"],["scan.model.dm_string_v1",["bytes.view_lit","metrics"]]]],["set","k",["+","k",1]],["set","pl",["scan.dm.payload_push_entry_v1","pl",["bytes.view_lit","payload"],["scan.dm.empty_map_v1"]]],["set","k",["+","k",1]],["let","pl_b",["std.vec.as_bytes","pl"]],["let","event_value",["scan.dm.map_from_entries_v1","k",["bytes.view","pl_b"]]],["scan.events._event_line_v1",["bytes.view","event_value"]]],"kind":"defn","name":"scan.events.metrics_usage_v1","params":[{"name":"seq","ty":"i32"},{"name":"run_id","ty":"bytes_view"},{"name":"payload_value","ty":"bytes"}],"result":"bytes"},{"body":["begin",["let","ts",["scan.events._ts_v1"]],["let","pl",["std.vec.with_capacity",768]],["let","k",0],["set","pl",["scan.dm.payload_push_entry_v1","pl",["bytes.view_lit","type"],["scan.model.dm_string_v1",["bytes.view_lit","scan.finished"]]]],["set","k",["+","k",1]],["set","pl",["scan.dm.payload_push_entry_v1","pl",["bytes.view_lit","run_id"],["scan.model.dm_string_v1","run_id"]]],["set","k",["+","k",1]],["set","pl",["scan.dm.payload_push_entry_v1","pl",["bytes.view_lit","seq"],["scan.model.dm_number_i32_v1","seq"]]],["set","k",["+","k",1]],["set","pl",["scan.dm.payload_push_entry_v1","pl",["bytes.view_lit","timestamp"],["scan.model.dm_string_v1",["bytes.view","ts"]]]],["set","k",["+","k",1]],["set","pl",["scan.dm.payload_push_entry_v1","pl",["bytes.view_lit","phase"],["scan.model.dm_string_v1",["bytes.view_lit","scan"]]]],["set","k",["+","k",1]],["set","pl",["scan.dm.payload_push_entry_v1","pl",["bytes.view_lit","status"],["scan.model.dm_string_v1","status"]]],["set","k",["+","k",1]],["set","pl",["scan.dm.payload_push_entry_v1","pl",["bytes.view_lit","score_available"],["scan.model.dm_bool_v1","score_available"]]],["set","k",["+","k",1]],["set","pl",["scan.dm.payload_push_entry_v1","pl",["bytes.view_lit","score_truth_status"],["scan.model.dm_string_v1","score_truth_status"]]],["set","k",["+","k",1]],["set","pl",["scan.dm.payload_push_entry_v1","pl",["bytes.view_lit","overall_score"],"overall_score_value"]],["set","k",["+","k",1]],["set","pl",["scan.dm.payload_push_entry_v1","pl",["bytes.view_lit","partial_score"],"partial_score_value"]],["set","k",["+","k",1]],["set","pl",["scan.dm.payload_push_entry_v1","pl",["bytes.view_lit","report_path"],["scan.model.dm_string_v1","report_path"]]],["set","k",["+","k",1]],["set","pl",["scan.dm.payload_push_entry_v1","pl",["bytes.view_lit","events_path"],["scan.model.dm_string_v1","events_path"]]],["set","k",["+","k",1]],["set","pl",["scan.dm.payload_push_entry_v1","pl",["bytes.view_lit","payload"],["scan.dm.empty_map_v1"]]],["set","k",["+","k",1]],["let","pl_b",["std.vec.as_bytes","pl"]],["let","event_value",["scan.dm.map_from_entries_v1","k",["bytes.view","pl_b"]]],["scan.events._event_line_v1",["bytes.view","event_value"]]],"kind":"defn","name":"scan.events.scan_finished_v1","params":[{"name":"seq","ty":"i32"},{"name":"run_id","ty":"bytes_view"},{"name":"status","ty":"bytes_view"},{"name":"score_available","ty":"i32"},{"name":"score_truth_status","ty":"bytes_view"},{"name":"overall_score_value","ty":"bytes"},{"name":"partial_score_value","ty":"bytes"},{"name":"report_path","ty":"bytes_view"},{"name":"events_path","ty":"bytes_view"}],"result":"bytes"},{"body":["begin",["let","ts",["scan.events._ts_v1"]],["let","pl",["std.vec.with_capacity",512]],["let","k",0],["set","pl",["scan.dm.payload_push_entry_v1","pl",["bytes.view_lit","type"],["scan.model.dm_string_v1",["bytes.view_lit","scan.started"]]]],["set","k",["+","k",1]],["set","pl",["scan.dm.payload_push_entry_v1","pl",["bytes.view_lit","run_id"],["scan.model.dm_string_v1","run_id"]]],["set","k",["+","k",1]],["set","pl",["scan.dm.payload_push_entry_v1","pl",["bytes.view_lit","seq"],["scan.model.dm_number_i32_v1","seq"]]],["set","k",["+","k",1]],["set","pl",["scan.dm.payload_push_entry_v1","pl",["bytes.view_lit","timestamp"],["scan.model.dm_string_v1",["bytes.view","ts"]]]],["set","k",["+","k",1]],["set","pl",["scan.dm.payload_push_entry_v1","pl",["bytes.view_lit","phase"],["scan.model.dm_string_v1",["bytes.view_lit","scan"]]]],["set","k",["+","k",1]],["set","pl",["scan.dm.payload_push_entry_v1","pl",["bytes.view_lit","target"],["scan.model.dm_string_v1","target"]]],["set","k",["+","k",1]],["set","pl",["scan.dm.payload_push_entry_v1","pl",["bytes.view_lit","transport"],["scan.model.dm_string_v1","transport"]]],["set","k",["+","k",1]],["set","pl",["scan.dm.payload_push_entry_v1","pl",["bytes.view_lit","payload"],["scan.dm.empty_map_v1"]]],["set","k",["+","k",1]],["let","pl_b",["std.vec.as_bytes","pl"]],["let","event_value",["scan.dm.map_from_entries_v1","k",["bytes.view","pl_b"]]],["scan.events._event_line_v1",["bytes.view","event_value"]]],"kind":"defn","name":"scan.events.scan_started_v1","params":[{"name":"seq","ty":"i32"},{"name":"run_id","ty":"bytes_view"},{"name":"target","ty":"bytes_view"},{"name":"transport","ty":"bytes_view"}],"result":"bytes"},{"body":["begin",["let","ts",["scan.events._ts_v1"]],["let","pl",["std.vec.with_capacity",768]],["let","k",0],["set","pl",["scan.dm.payload_push_entry_v1","pl",["bytes.view_lit","type"],["scan.model.dm_string_v1",["bytes.view_lit","scan.score.preview"]]]],["set","k",["+","k",1]],["set","pl",["scan.dm.payload_push_entry_v1","pl",["bytes.view_lit","run_id"],["scan.model.dm_string_v1","run_id"]]],["set","k",["+","k",1]],["set","pl",["scan.dm.payload_push_entry_v1","pl",["bytes.view_lit","seq"],["scan.model.dm_number_i32_v1","seq"]]],["set","k",["+","k",1]],["set","pl",["scan.dm.payload_push_entry_v1","pl",["bytes.view_lit","timestamp"],["scan.model.dm_string_v1",["bytes.view","ts"]]]],["set","k",["+","k",1]],["set","pl",["scan.dm.payload_push_entry_v1","pl",["bytes.view_lit","phase"],["scan.model.dm_string_v1",["bytes.view_lit","score"]]]],["set","k",["+","k",1]],["set","pl",["scan.dm.payload_push_entry_v1","pl",["bytes.view_lit","score_available"],["scan.model.dm_bool_v1","score_available"]]],["set","k",["+","k",1]],["set","pl",["scan.dm.payload_push_entry_v1","pl",["bytes.view_lit","score_truth_status"],["scan.model.dm_string_v1","score_truth_status"]]],["set","k",["+","k",1]],["set","pl",["scan.dm.payload_push_entry_v1","pl",["bytes.view_lit","overall_score"],"overall_score_value"]],["set","k",["+","k",1]],["set","pl",["scan.dm.payload_push_entry_v1","pl",["bytes.view_lit","partial_score"],"partial_score_value"]],["set","k",["+","k",1]],["set","pl",["scan.dm.payload_push_entry_v1","pl",["bytes.view_lit","payload"],["scan.dm.empty_map_v1"]]],["set","k",["+","k",1]],["let","pl_b",["std.vec.as_bytes","pl"]],["let","event_value",["scan.dm.map_from_entries_v1","k",["bytes.view","pl_b"]]],["scan.events._event_line_v1",["bytes.view","event_value"]]],"kind":"defn","name":"scan.events.score_preview_v1","params":[{"name":"seq","ty":"i32"},{"name":"run_id","ty":"bytes_view"},{"name":"score_available","ty":"i32"},{"name":"score_truth_status","ty":"bytes_view"},{"name":"overall_score_value","ty":"bytes"},{"name":"partial_score_value","ty":"bytes"}],"result":"bytes"},{"body":["begin",["let","ts",["scan.events._ts_v1"]],["let","pl",["std.vec.with_capacity",512]],["let","k",0],["set","pl",["scan.dm.payload_push_entry_v1","pl",["bytes.view_lit","ok"],["scan.model.dm_bool_v1","ok"]]],["set","k",["+","k",1]],["set","pl",["scan.dm.payload_push_entry_v1","pl",["bytes.view_lit","stage"],["scan.model.dm_string_v1","stage"]]],["set","k",["+","k",1]],["set","pl",["scan.dm.payload_push_entry_v1","pl",["bytes.view_lit","phase"],["scan.model.dm_string_v1","stage"]]],["set","k",["+","k",1]],["set","pl",["scan.dm.payload_push_entry_v1","pl",["bytes.view_lit","run_id"],["scan.model.dm_string_v1","run_id"]]],["set","k",["+","k",1]],["set","pl",["scan.dm.payload_push_entry_v1","pl",["bytes.view_lit","seq"],["scan.model.dm_number_i32_v1","seq"]]],["set","k",["+","k",1]],["set","pl",["scan.dm.payload_push_entry_v1","pl",["bytes.view_lit","timestamp"],["scan.model.dm_string_v1",["bytes.view","ts"]]]],["set","k",["+","k",1]],["set","pl",["scan.dm.payload_push_entry_v1","pl",["bytes.view_lit","type"],["scan.model.dm_string_v1",["bytes.view_lit","scan.stage.finished"]]]],["set","k",["+","k",1]],["set","pl",["scan.dm.payload_push_entry_v1","pl",["bytes.view_lit","payload"],["scan.dm.empty_map_v1"]]],["set","k",["+","k",1]],["let","pl_b",["std.vec.as_bytes","pl"]],["let","event_value",["scan.dm.map_from_entries_v1","k",["bytes.view","pl_b"]]],["scan.events._event_line_v1",["bytes.view","event_value"]]],"kind":"defn","name":"scan.events.stage_finished_v1","params":[{"name":"seq","ty":"i32"},{"name":"run_id","ty":"bytes_view"},{"name":"stage","ty":"bytes_view"},{"name":"ok","ty":"i32"}],"result":"bytes"},{"body":["begin",["let","ts",["scan.events._ts_v1"]],["let","pl",["std.vec.with_capacity",512]],["let","k",0],["set","pl",["scan.dm.payload_push_entry_v1","pl",["bytes.view_lit","stage"],["scan.model.dm_string_v1","stage"]]],["set","k",["+","k",1]],["set","pl",["scan.dm.payload_push_entry_v1","pl",["bytes.view_lit","phase"],["scan.model.dm_string_v1","stage"]]],["set","k",["+","k",1]],["set","pl",["scan.dm.payload_push_entry_v1","pl",["bytes.view_lit","run_id"],["scan.model.dm_string_v1","run_id"]]],["set","k",["+","k",1]],["set","pl",["scan.dm.payload_push_entry_v1","pl",["bytes.view_lit","seq"],["scan.model.dm_number_i32_v1","seq"]]],["set","k",["+","k",1]],["set","pl",["scan.dm.payload_push_entry_v1","pl",["bytes.view_lit","timestamp"],["scan.model.dm_string_v1",["bytes.view","ts"]]]],["set","k",["+","k",1]],["set","pl",["scan.dm.payload_push_entry_v1","pl",["bytes.view_lit","type"],["scan.model.dm_string_v1",["bytes.view_lit","scan.stage.started"]]]],["set","k",["+","k",1]],["set","pl",["scan.dm.payload_push_entry_v1","pl",["bytes.view_lit","payload"],["scan.dm.empty_map_v1"]]],["set","k",["+","k",1]],["let","pl_b",["std.vec.as_bytes","pl"]],["let","event_value",["scan.dm.map_from_entries_v1","k",["bytes.view","pl_b"]]],["scan.events._event_line_v1",["bytes.view","event_value"]]],"kind":"defn","name":"scan.events.stage_started_v1","params":[{"name":"seq","ty":"i32"},{"name":"run_id","ty":"bytes_view"},{"name":"stage","ty":"bytes_view"}],"result":"bytes"}],"imports":["ext.data_model","scan.dm","scan.model","scan.time","std.cli.jsonl","std.vec"],"kind":"module","module_id":"scan.events","schema_version":"x07.x07ast@0.8.0"}
