{"decls":[{"kind":"export","names":["scan.security_rules.auth_missing_finding_v1","scan.security_rules.auth_protection_status_v1","scan.security_rules.command_risk_finding_v1","scan.security_rules.descriptor_bloat_finding_v1","scan.security_rules.injection_finding_v1"]},{"body":["begin",["let","pl",["std.vec.with_capacity",64]],["let","k",0],["set","pl",["scan.dm.payload_push_entry_v1","pl","key",["scan.model.dm_number_i32_v1","value"]]],["set","k",["+","k",1]],["let","pl_b",["std.vec.as_bytes","pl"]],["scan.dm.map_from_entries_v1","k",["bytes.view","pl_b"]]],"kind":"defn","name":"scan.security_rules._evidence_i32_v1","params":[{"name":"key","ty":"bytes_view"},{"name":"value","ty":"i32"}],"result":"bytes"},{"body":["if",["||",["=","status_code",401],["=","status_code",403]],1,0],"kind":"defn","name":"scan.security_rules._status_is_auth_challenge_v1","params":[{"name":"status_code","ty":"i32"}],"result":"i32"},{"body":["scan.model.finding_v1",["bytes.view_lit","security"],["bytes.view_lit","SEC-AUTH-MISCONFIG"],["bytes.view_lit","warning"],["bytes.view_lit","Remote endpoint allowed unauthenticated access"],["bytes.view_lit","A remote HTTP MCP endpoint responded without an authentication challenge, which expands the exposed attack surface."],["scan.security_rules._evidence_i32_v1",["bytes.view_lit","observed_status_code"],"observed_status_code"],["bytes.view_lit","Require bearer or equivalent authentication for remote HTTP deployments."],["bytes.view_lit","https://x07.io/docs/hardproof/findings/SEC-AUTH-MISCONFIG"]],"kind":"defn","name":"scan.security_rules.auth_missing_finding_v1","params":[{"name":"observed_status_code","ty":"i32"}],"result":"bytes"},{"body":["begin",["if",["||",["=",["scan.security_rules._status_is_auth_challenge_v1","init_status"],1],["||",["=",["scan.security_rules._status_is_auth_challenge_v1","list_status_a"],1],["=",["scan.security_rules._status_is_auth_challenge_v1","list_status_b"],1]]],["return",["bytes.lit","required"]],0],["if",["||",["&&",[">=","init_status",0],["<","init_status",400]],["||",["&&",[">=","list_status_a",0],["<","list_status_a",400]],["&&",[">=","list_status_b",0],["<","list_status_b",400]]]],["bytes.lit","missing"],["bytes.lit","unknown"]]],"kind":"defn","name":"scan.security_rules.auth_protection_status_v1","params":[{"name":"init_status","ty":"i32"},{"name":"list_status_a","ty":"i32"},{"name":"list_status_b","ty":"i32"}],"result":"bytes"},{"body":["scan.model.finding_v1",["bytes.view_lit","security"],["bytes.view_lit","SEC-COMMAND-RISK-PATTERN"],["bytes.view_lit","warning"],["bytes.view_lit","Command-risk parameter surface"],["bytes.view_lit","Tool metadata exposes command or shell execution patterns that deserve manual review."],["scan.security_rules._evidence_i32_v1",["bytes.view_lit","pattern_count"],"pattern_count"],["bytes.view_lit","Prefer structured arguments over free-form command execution surfaces."],["bytes.view_lit","https://x07.io/docs/hardproof/findings/SEC-COMMAND-RISK-PATTERN"]],"kind":"defn","name":"scan.security_rules.command_risk_finding_v1","params":[{"name":"pattern_count","ty":"i32"}],"result":"bytes"},{"body":["scan.model.finding_v1",["bytes.view_lit","security"],["bytes.view_lit","SEC-DESCRIPTOR-BLOAT"],["bytes.view_lit","warning"],["bytes.view_lit","Oversized tool descriptors"],["bytes.view_lit","Very large tool metadata increases prompt-injection surface and review burden."],["scan.security_rules._evidence_i32_v1",["bytes.view_lit","descriptor_bytes"],"descriptor_bytes"],["bytes.view_lit","Trim descriptions, examples, and redundant schema prose."],["bytes.view_lit","https://x07.io/docs/hardproof/findings/SEC-DESCRIPTOR-BLOAT"]],"kind":"defn","name":"scan.security_rules.descriptor_bloat_finding_v1","params":[{"name":"descriptor_bytes","ty":"i32"}],"result":"bytes"},{"body":["scan.model.finding_v1",["bytes.view_lit","security"],["bytes.view_lit","SEC-INJECTION-PATTERN"],["bytes.view_lit","warning"],["bytes.view_lit","Suspicious injection pattern"],["bytes.view_lit","Tool metadata contains imperative prompt-style instructions that expand the injection surface."],["scan.security_rules._evidence_i32_v1",["bytes.view_lit","pattern_count"],"pattern_count"],["bytes.view_lit","Remove prompt-injection-like instructions from tool metadata."],["bytes.view_lit","https://x07.io/docs/hardproof/findings/SEC-INJECTION-PATTERN"]],"kind":"defn","name":"scan.security_rules.injection_finding_v1","params":[{"name":"pattern_count","ty":"i32"}],"result":"bytes"}],"imports":["scan.dm","scan.model","std.vec"],"kind":"module","module_id":"scan.security_rules","schema_version":"x07.x07ast@0.8.0"}
